bbpy/__init__.py
bbpy/bbpy.py
bbpy/pbuf/app_pb2.py
bbpy/pbuf/app_pb2_grpc.py
bbpy/pbuf/attr_pb2.py
bbpy-1.0.6.dist-info/LICENSE
bbpy-1.0.6.dist-info/METADATA
bbpy-1.0.6.dist-info/WHEEL
bbpy-1.0.6.dist-info/top_level.txt
bbpy-1.0.6.dist-info/RECORD
