Metadata-Version: 2.1
Name: bbpy
Version: 1.0.6
Summary: This package provides a Python interface to biobtree
Home-page: https://github.com/tamerh/biobtreePy
Author: Tamer Gur
Author-email: tgur@ebi.ac.uk
License: MIT license
Keywords: bioinformatics,identifiers,mapping,biobtree
Platform: UNKNOWN
Requires-Dist: grpcio (>=1.24.3)
Requires-Dist: protobuf (>=3.5.0)
Requires-Dist: requests (>=2.20)
